{"sdg_goal":1,"indicator_number":1.5,"graph_title":"global_indicators.1-5-title","indicator_sort_order":"01-05-01","data_non_statistical":false,"graph_type":"line","computation_units":"Prozent","data_start_values":[{"field":"Region","value":"Ingolstadt"},{"field":"Region","value":"Bayern"}],"national_geographical_coverage":"Ingolstadt","computation_definitions":null,"SOURCE_TYPE":"Amt f\u00fcr Statistik und Stadtforschung","source_earliest_available_1":2019,"source_periodicity_1":"J\u00e4hrlich","language":"de","published":true,"reporting_status":"complete","page_content":"Empf\u00e4nger/-innen von Grundsicherung nach SGB II insgesamt in % der Einwohner unter 65.\n","national_metadata_updated_date":"2023-04-05","national_data_updated_date":"2023-04-03","target_number":"1.5","goal_number":"1","indicator_name":"global_indicators.1-5-title"}